linear_crf/__init__.py
linear_crf/linear_crf.py
linear_crf_torch-0.0.1.dist-info/LICENSE
linear_crf_torch-0.0.1.dist-info/METADATA
linear_crf_torch-0.0.1.dist-info/WHEEL
linear_crf_torch-0.0.1.dist-info/top_level.txt
linear_crf_torch-0.0.1.dist-info/RECORD
